pydantic_db_backend_exceptions/__init__.py
pydantic_db_backend_exceptions-1.0.0.dist-info/METADATA
pydantic_db_backend_exceptions-1.0.0.dist-info/WHEEL
pydantic_db_backend_exceptions-1.0.0.dist-info/RECORD
