Metadata-Version: 2.1
Name: pydantic-db-backend-exceptions
Version: 1.0.0
Summary: 
Author: mba
Author-email: bartel@electronic-shop.lu
Requires-Python: >=3.11,<4.0
Classifier: Programming Language :: Python :: 3
Classifier: Programming Language :: Python :: 3.11
Requires-Dist: webexception (>=1.0.4,<2.0.0)
